restful_starlette/__init__.py
restful_starlette/blueprint.py
restful_starlette/apps/__init__.py
restful_starlette/apps/swagger/__init__.py
restful_starlette/apps/swagger/app.py
restful_starlette/apps/swagger/endpoint.py
restful_starlette/apps/swagger/generator.py
restful_starlette/apps/swagger/routes.py
restful_starlette/apps/swagger/statics/favicon-16x16.png
restful_starlette/apps/swagger/statics/favicon-32x32.png
restful_starlette/apps/swagger/statics/index.html
restful_starlette/apps/swagger/statics/oauth2-redirect.html
restful_starlette/apps/swagger/statics/swagger-ui-bundle.js
restful_starlette/apps/swagger/statics/swagger-ui-bundle.js.map
restful_starlette/apps/swagger/statics/swagger-ui-es-bundle-core.js
restful_starlette/apps/swagger/statics/swagger-ui-es-bundle-core.js.map
restful_starlette/apps/swagger/statics/swagger-ui-es-bundle.js
restful_starlette/apps/swagger/statics/swagger-ui-es-bundle.js.map
restful_starlette/apps/swagger/statics/swagger-ui-standalone-preset.js
restful_starlette/apps/swagger/statics/swagger-ui-standalone-preset.js.map
restful_starlette/apps/swagger/statics/swagger-ui.css
restful_starlette/apps/swagger/statics/swagger-ui.css.map
restful_starlette/apps/swagger/statics/swagger-ui.js
restful_starlette/apps/swagger/statics/swagger-ui.js.map
restful_starlette/command/__init__.py
restful_starlette/command/admin.py
restful_starlette/command/file_content.py
restful_starlette/conf/__init__.py
restful_starlette/conf/base.py
restful_starlette/conf/db.py
restful_starlette/exception/__init__.py
restful_starlette/exception/exceptions.py
restful_starlette/exception/handlers.py
restful_starlette/http/__init__.py
restful_starlette/http/endpoint.py
restful_starlette/http/permissions.py
restful_starlette/http/response.py
restful_starlette/http/restful.py
restful_starlette/http/transport.py
restful_starlette/log/__init__.py
restful_starlette/log/structlog.py
restful_starlette/middleware/__init__.py
restful_starlette/middleware/authenticate.py
restful_starlette-0.0.4.dist-info/LICENSE
restful_starlette-0.0.4.dist-info/METADATA
restful_starlette-0.0.4.dist-info/WHEEL
restful_starlette-0.0.4.dist-info/top_level.txt
restful_starlette-0.0.4.dist-info/RECORD
