Metadata-Version: 2.1
Name: restful-starlette
Version: 0.0.4
Summary: A restful API kit for starlette
Author: TianMa Chen
Author-email: 819252022@qq.com
License: BSD-3-Clause
Platform: UNKNOWN
Requires-Python: >=3.7
License-File: LICENSE
Requires-Dist: aerich (==0.6.2)
Requires-Dist: aiomysql (==0.0.22)
Requires-Dist: aiosqlite (==0.17.0)
Requires-Dist: anyio (==3.4.0)
Requires-Dist: asgiref (==3.4.1)
Requires-Dist: certifi (==2021.10.8)
Requires-Dist: charset-normalizer (==2.0.9)
Requires-Dist: click (==8.0.3)
Requires-Dist: ddlparse (==1.10.0)
Requires-Dist: dictdiffer (==0.9.0)
Requires-Dist: h11 (==0.12.0)
Requires-Dist: httpcore (==0.14.3)
Requires-Dist: httpx (==0.21.1)
Requires-Dist: idna (==3.3)
Requires-Dist: iso8601 (==0.1.16)
Requires-Dist: Jinja2 (==3.0.3)
Requires-Dist: MarkupSafe (==2.0.1)
Requires-Dist: Nuitka (==0.6.18.5)
Requires-Dist: passlib (==1.7.4)
Requires-Dist: pydantic (==1.8.2)
Requires-Dist: PyJWT (==2.3.0)
Requires-Dist: PyMySQL (==0.9.3)
Requires-Dist: pyparsing (==3.0.6)
Requires-Dist: pypika-tortoise (==0.1.3)
Requires-Dist: python-dotenv (==0.19.2)
Requires-Dist: pytz (==2021.3)
Requires-Dist: PyYAML (==6.0)
Requires-Dist: rfc3986 (==1.5.0)
Requires-Dist: sniffio (==1.2.0)
Requires-Dist: starlette (==0.17.1)
Requires-Dist: starlette-context (==0.3.3)
Requires-Dist: structlog (==21.4.0)
Requires-Dist: tomlkit (==0.9.2)
Requires-Dist: tortoise-orm (==0.18.1)
Requires-Dist: typing-extensions (==4.0.1)
Requires-Dist: uvicorn (==0.15.0)
Requires-Dist: websockets (==10.1)
Requires-Dist: micro-kits (==0.0.2)
